mosec-0.9.5.data/scripts/mosec
mosec-0.9.5.dist-info/METADATA
mosec-0.9.5.dist-info/WHEEL
mosec-0.9.5.dist-info/licenses/LICENSE
mosec/__init__.py
mosec/args.py
mosec/coordinator.py
mosec/dry_run.py
mosec/env.py
mosec/errors.py
mosec/log.py
mosec/mixin/__init__.py
mosec/mixin/msgpack_worker.py
mosec/mixin/numbin_worker.py
mosec/mixin/plasma_worker.py
mosec/mixin/redis_worker.py
mosec/mixin/typed_worker.py
mosec/protocol.py
mosec/py.typed
mosec/runtime.py
mosec/server.py
mosec/utils.py
mosec/worker.py
mosec-0.9.5.dist-info/RECORD
