Metadata-Version: 2.4
Name: mosec
Version: 0.9.5
Classifier: Environment :: GPU
Classifier: Intended Audience :: Developers
Classifier: Intended Audience :: Science/Research
Classifier: License :: OSI Approved :: Apache Software License
Classifier: Programming Language :: Python :: 3 :: Only
Classifier: Programming Language :: Python :: 3.9
Classifier: Programming Language :: Python :: 3.10
Classifier: Programming Language :: Python :: 3.11
Classifier: Programming Language :: Python :: 3.12
Classifier: Programming Language :: Python :: 3.13
Classifier: Programming Language :: Python :: Implementation :: CPython
Classifier: Programming Language :: Python :: Implementation :: PyPy
Classifier: Programming Language :: Rust
Classifier: Topic :: Scientific/Engineering :: Artificial Intelligence
Classifier: Topic :: Software Development :: Libraries :: Python Modules
Classifier: Topic :: Software Development :: Build Tools
Requires-Dist: msgspec>=0.19.0 ; extra == 'validation'
Requires-Dist: redis>=5.2.1 ; extra == 'redis'
Requires-Dist: msgpack>=1.1.0 ; extra == 'msgpack'
Requires-Dist: numbin>=0.5.0 ; extra == 'numbin'
Provides-Extra: validation
Provides-Extra: redis
Provides-Extra: msgpack
Provides-Extra: numbin
License-File: LICENSE
Summary: Model Serving made Efficient in the Cloud
Keywords: machine learning,deep learning,model serving
Author: Keming <kemingy94@gmail.com>, Zichen <lkevinzc@gmail.com>
Author-email: Keming <kemingy94@gmail.com>, Zichen <lkevinzc@gmail.com>
License: Apache-2.0
Requires-Python: >=3.9
Project-URL: homepage, https://mosecorg.github.io/
Project-URL: documentation, https://mosecorg.github.io/mosec/
Project-URL: repository, https://github.com/mosecorg/mosec
Project-URL: changelog, https://github.com/mosecorg/mosec/releases
